LICENSE
MANIFEST.in
README.rst
setup.py
lo99ing/__init__.py
lo99ing/_bootstrap.py
lo99ing/formatter.py
lo99ing/handlers.py
lo99ing/level.py
lo99ing/logger.py
lo99ing/misc.py
lo99ing/utils.py
lo99ing/version.py
lo99ing.egg-info/PKG-INFO
lo99ing.egg-info/SOURCES.txt
lo99ing.egg-info/dependency_links.txt
lo99ing.egg-info/top_level.txt