Metadata-Version: 1.1
Name: lo99ing
Version: 0.1.1
Summary: Python logging, configured the way I like it.
Home-page: https://github.com/shx2/lo99ing
Author: shx2
Author-email: shx222@gmail.com
License: MIT
Keywords: logging logger logfile
Platform: POSIX
Platform: Windows
Classifier: Programming Language :: Python :: 3
Classifier: Development Status :: 3 - Alpha
Classifier: Intended Audience :: Developers
Classifier: Topic :: Software Development
Classifier: License :: OSI Approved :: MIT License
Classifier: Operating System :: POSIX
Classifier: Operating System :: Microsoft :: Windows
